<?xml version='1.0' encoding='UTF-8'?>
<Gesture AppName="Gestures" AppVer="3.5.0.0" Date="2019/12/19" Milliseconds="200" Name="t17" NumPts="82" Speed="test" Subject="test" TimeOfDay="16:59:58">
  <Partition>
    <Spec Index="40" Stroke="0"/>
    <Spec Index="81" Stroke="1"/>
  </Partition>
  <Stroke index="1">
    <Point T="0" X="560" Y="200"/>
    <Point T="5" X="561" Y="201"/>
    <Point T="10" X="562" Y="201"/>
    <Point T="15" X="563" Y="201"/>
    <Point T="20" X="565" Y="202"/>
    <Point T="25" X="566" Y="202"/>
    <Point T="30" X="568" Y="202"/>
    <Point T="35" X="569" Y="202"/>
    <Point T="40" X="571" Y="203"/>
    <Point T="45" X="573" Y="203"/>
    <Point T="50" X="574" Y="204"/>
    <Point T="55" X="576" Y="204"/>
    <Point T="60" X="578" Y="204"/>
    <Point T="65" X="579" Y="205"/>
    <Point T="70" X="581" Y="205"/>
    <Point T="75" X="583" Y="205"/>
    <Point T="80" X="584" Y="206"/>
    <Point T="85" X="586" Y="206"/>
    <Point T="90" X="588" Y="206"/>
    <Point T="95" X="589" Y="207"/>
    <Point T="100" X="591" Y="207"/>
    <Point T="105" X="592" Y="207"/>
    <Point T="110" X="594" Y="208"/>
    <Point T="115" X="595" Y="208"/>
    <Point T="120" X="597" Y="208"/>
    <Point T="125" X="598" Y="209"/>
    <Point T="130" X="600" Y="209"/>
    <Point T="135" X="601" Y="209"/>
    <Point T="140" X="602" Y="210"/>
    <Point T="145" X="604" Y="210"/>
    <Point T="150" X="605" Y="210"/>
    <Point T="155" X="606" Y="210"/>
    <Point T="160" X="608" Y="211"/>
    <Point T="165" X="610" Y="211"/>
    <Point T="170" X="613" Y="212"/>
    <Point T="175" X="617" Y="213"/>
    <Point T="180" X="621" Y="214"/>
    <Point T="185" X="623" Y="214"/>
    <Point T="190" X="625" Y="214"/>
    <Point T="195" X="626" Y="215"/>
    <Point T="200" X="626" Y="215"/>
  </Stroke>
  <Stroke index="2">
    <Point T="0" X="600" Y="200"/>
    <Point T="5" X="600" Y="202"/>
    <Point T="10" X="600" Y="203"/>
    <Point T="15" X="599" Y="206"/>
    <Point T="20" X="599" Y="208"/>
    <Point T="25" X="598" Y="210"/>
    <Point T="30" X="598" Y="212"/>
    <Point T="35" X="597" Y="214"/>
    <Point T="40" X="597" Y="216"/>
    <Point T="45" X="596" Y="218"/>
    <Point T="50" X="596" Y="220"/>
    <Point T="55" X="595" Y="222"/>
    <Point T="60" X="595" Y="224"/>
    <Point T="65" X="594" Y="226"/>
    <Point T="70" X="594" Y="228"/>
    <Point T="75" X="593" Y="230"/>
    <Point T="80" X="593" Y="232"/>
    <Point T="85" X="593" Y="233"/>
    <Point T="90" X="592" Y="235"/>
    <Point T="95" X="592" Y="237"/>
    <Point T="100" X="592" Y="238"/>
    <Point T="105" X="591" Y="240"/>
    <Point T="110" X="591" Y="241"/>
    <Point T="115" X="590" Y="243"/>
    <Point T="120" X="590" Y="244"/>
    <Point T="125" X="590" Y="246"/>
    <Point T="130" X="589" Y="247"/>
    <Point T="135" X="589" Y="248"/>
    <Point T="140" X="589" Y="250"/>
    <Point T="145" X="588" Y="252"/>
    <Point T="150" X="588" Y="253"/>
    <Point T="155" X="588" Y="255"/>
    <Point T="160" X="587" Y="256"/>
    <Point T="165" X="587" Y="258"/>
    <Point T="170" X="587" Y="260"/>
    <Point T="175" X="586" Y="261"/>
    <Point T="180" X="586" Y="263"/>
    <Point T="185" X="586" Y="264"/>
    <Point T="190" X="585" Y="265"/>
    <Point T="195" X="585" Y="266"/>
    <Point T="200" X="585" Y="267"/>
  </Stroke>
</Gesture>
