<?xml version="1.0" encoding="utf-8"?>
<Gesture AppName="Gestures" AppVer="3.5.0.0" Date="2020/1/25" Milliseconds="300" Name="arrowhead41" NumPts="118" Speed="Custom" Subject="Custom" TimeOfDay="23:34:16">
  <Partition>
    <Spec Stroke="0" Index="60" />
    <Spec Stroke="1" Index="89" />
    <Spec Stroke="1" Index="118" />
  </Partition>
  <Stroke index="1">
    <Point T="0" X="600" Y="200" />
    <Point T="5" X="601" Y="200" />
    <Point T="10" X="602" Y="200" />
    <Point T="15" X="603" Y="200" />
    <Point T="20" X="604" Y="200" />
    <Point T="25" X="605" Y="199" />
    <Point T="30" X="607" Y="199" />
    <Point T="35" X="609" Y="199" />
    <Point T="40" X="610" Y="199" />
    <Point T="45" X="612" Y="198" />
    <Point T="50" X="614" Y="198" />
    <Point T="55" X="616" Y="198" />
    <Point T="60" X="618" Y="198" />
    <Point T="65" X="621" Y="197" />
    <Point T="70" X="623" Y="197" />
    <Point T="75" X="625" Y="197" />
    <Point T="80" X="628" Y="196" />
    <Point T="85" X="630" Y="196" />
    <Point T="90" X="633" Y="196" />
    <Point T="95" X="635" Y="195" />
    <Point T="100" X="638" Y="195" />
    <Point T="105" X="640" Y="195" />
    <Point T="110" X="643" Y="194" />
    <Point T="115" X="645" Y="194" />
    <Point T="120" X="648" Y="194" />
    <Point T="125" X="651" Y="193" />
    <Point T="130" X="653" Y="193" />
    <Point T="135" X="656" Y="193" />
    <Point T="140" X="658" Y="192" />
    <Point T="145" X="661" Y="192" />
    <Point T="150" X="664" Y="192" />
    <Point T="155" X="666" Y="192" />
    <Point T="160" X="669" Y="191" />
    <Point T="165" X="671" Y="191" />
    <Point T="170" X="674" Y="191" />
    <Point T="175" X="676" Y="190" />
    <Point T="180" X="679" Y="190" />
    <Point T="185" X="681" Y="190" />
    <Point T="190" X="683" Y="190" />
    <Point T="195" X="686" Y="189" />
    <Point T="200" X="688" Y="189" />
    <Point T="205" X="690" Y="189" />
    <Point T="210" X="693" Y="189" />
    <Point T="215" X="695" Y="188" />
    <Point T="220" X="697" Y="188" />
    <Point T="225" X="699" Y="188" />
    <Point T="230" X="701" Y="188" />
    <Point T="235" X="704" Y="188" />
    <Point T="240" X="706" Y="187" />
    <Point T="245" X="708" Y="187" />
    <Point T="250" X="710" Y="187" />
    <Point T="255" X="712" Y="187" />
    <Point T="260" X="714" Y="187" />
    <Point T="265" X="716" Y="186" />
    <Point T="270" X="717" Y="186" />
    <Point T="275" X="719" Y="186" />
    <Point T="280" X="721" Y="185" />
    <Point T="285" X="723" Y="185" />
    <Point T="290" X="724" Y="184" />
    <Point T="295" X="726" Y="184" />
    <Point T="300" X="728" Y="184" />
  </Stroke>
  <Stroke index="2">
    <Point T="0" X="680" Y="160" />
    <Point T="5" X="681" Y="161" />
    <Point T="10" X="682" Y="162" />
    <Point T="15" X="683" Y="163" />
    <Point T="20" X="684" Y="164" />
    <Point T="25" X="684" Y="166" />
    <Point T="30" X="685" Y="167" />
    <Point T="35" X="686" Y="169" />
    <Point T="40" X="687" Y="170" />
    <Point T="45" X="688" Y="171" />
    <Point T="50" X="689" Y="173" />
    <Point T="55" X="689" Y="174" />
    <Point T="60" X="690" Y="176" />
    <Point T="65" X="691" Y="178" />
    <Point T="70" X="692" Y="179" />
    <Point T="75" X="693" Y="181" />
    <Point T="80" X="694" Y="182" />
    <Point T="85" X="695" Y="184" />
    <Point T="90" X="696" Y="185" />
    <Point T="95" X="697" Y="187" />
    <Point T="100" X="698" Y="188" />
    <Point T="105" X="699" Y="189" />
    <Point T="110" X="700" Y="191" />
    <Point T="115" X="701" Y="192" />
    <Point T="120" X="702" Y="194" />
    <Point T="125" X="702" Y="195" />
    <Point T="130" X="703" Y="196" />
    <Point T="135" X="703" Y="197" />
    <Point T="140" X="703" Y="199" />
    <Point T="145" X="702" Y="200" />
    <Point T="150" X="702" Y="201" />
    <Point T="155" X="700" Y="201" />
    <Point T="160" X="699" Y="202" />
    <Point T="165" X="697" Y="203" />
    <Point T="170" X="695" Y="204" />
    <Point T="175" X="693" Y="205" />
    <Point T="180" X="691" Y="206" />
    <Point T="185" X="689" Y="207" />
    <Point T="190" X="687" Y="208" />
    <Point T="195" X="684" Y="209" />
    <Point T="200" X="682" Y="210" />
    <Point T="205" X="680" Y="212" />
    <Point T="210" X="678" Y="213" />
    <Point T="215" X="677" Y="214" />
    <Point T="220" X="675" Y="215" />
    <Point T="225" X="674" Y="217" />
    <Point T="230" X="672" Y="218" />
    <Point T="235" X="670" Y="219" />
    <Point T="240" X="668" Y="221" />
    <Point T="245" X="666" Y="222" />
    <Point T="250" X="664" Y="223" />
    <Point T="255" X="662" Y="224" />
    <Point T="260" X="661" Y="225" />
    <Point T="265" X="660" Y="226" />
    <Point T="270" X="659" Y="226" />
    <Point T="275" X="658" Y="227" />
    <Point T="280" X="658" Y="228" />
    <Point T="285" X="657" Y="228" />
  </Stroke>
</Gesture>